{
    "Ar36": {
        "error": 0.004429162268602173, 
        "filter_outliers_dict": {
            "filter_outliers": true, 
            "iterations": 2, 
            "std_devs": 2
        }, 
        "fit": "Parabolic", 
        "value": 1.3634963733249683
    }, 
    "Ar37": {
        "error": 0.020290736680417663, 
        "filter_outliers_dict": {
            "filter_outliers": true, 
            "iterations": 2, 
            "std_devs": 2
        }, 
        "fit": "linear", 
        "value": -0.07684457632120754
    }, 
    "Ar38": {
        "error": 0.0008196213378815174, 
        "filter_outliers_dict": {
            "filter_outliers": true, 
            "iterations": 2, 
            "std_devs": 2
        }, 
        "fit": "linear", 
        "value": 0.2584433593147649
    }, 
    "Ar39": {
        "error": 0.04982403373581901, 
        "filter_outliers_dict": {
            "filter_outliers": true, 
            "iterations": 2, 
            "std_devs": 2
        }, 
        "fit": "Parabolic", 
        "value": -0.023509719433344352
    }, 
    "Ar40": {
        "error": 0.08992824895962646, 
        "filter_outliers_dict": {
            "filter_outliers": true, 
            "iterations": 2, 
            "std_devs": 2
        }, 
        "fit": "Parabolic", 
        "value": 409.01017935774445
    }, 
    "PHHCbs": {
        "error": 0.0, 
        "filter_outliers_dict": {
            "filter_outliers": false, 
            "iterations": 1, 
            "std_devs": 2
        }, 
        "fit": "linear", 
        "value": 0.0826608989160475
    }
}